Metadata-Version: 2.1
Name: ibm-data-virtualization-on-cloud
Version: 0.0.3
Summary: The IBM Data Virtualization on Cloud Python SDK
Home-page: https://github.com/IBM/data-virtualization-on-cloud-python-sdk
Author: IBM
Author-email: devxsdk@us.ibm.com
License: Apache 2.0
Keywords: ibm_data_virtualization_on_cloud
Platform: UNKNOWN
Classifier: Programming Language :: Python
Classifier: Programming Language :: Python :: 3
Classifier: Programming Language :: Python :: 3.6
Classifier: Programming Language :: Python :: 3.7
Classifier: Programming Language :: Python :: 3.8
Classifier: Programming Language :: Python :: 3.9
Classifier: Development Status :: 4 - Beta
Classifier: Intended Audience :: Developers
Classifier: License :: OSI Approved :: Apache Software License
Classifier: Operating System :: OS Independent
Classifier: Topic :: Software Development :: Libraries :: Python Modules
Classifier: Topic :: Software Development :: Libraries :: Application Frameworks
License-File: LICENSE
